romanutils/__init__.py
romanutils/core.py
romanutils-0.1.0.dist-info/METADATA
romanutils-0.1.0.dist-info/WHEEL
romanutils-0.1.0.dist-info/top_level.txt
romanutils-0.1.0.dist-info/RECORD
