Metadata-Version: 2.4
Name: romanutils
Version: 0.1.0
Summary: A Python library for Roman numeral manipulation
Home-page: https://github.com/Cyrus-spc-tech/Romanutils.git
Author: Tanish
Classifier: Programming Language :: Python :: 3
Requires-Python: >=3.6
Dynamic: author
Dynamic: classifier
Dynamic: description
Dynamic: description-content-type
Dynamic: home-page
Dynamic: requires-python
Dynamic: summary
